spmp/__init__.py
spmp/__main__.py
spmp/_version.py
spmp/naming_convention.py
spmp-0.2.3.dist-info/LICENSE
spmp-0.2.3.dist-info/METADATA
spmp-0.2.3.dist-info/WHEEL
spmp-0.2.3.dist-info/entry_points.txt
spmp-0.2.3.dist-info/top_level.txt
spmp-0.2.3.dist-info/RECORD
