Metadata-Version: 2.1
Name: spmp
Version: 0.2.3
Summary: Satellite Products Metadata Parser
Author-email: "P. MANCHON" <pierre.manchon@pm.me>
License: GNU GENERAL PUBLIC LICENSE
Project-URL: tracker, https://todo.sr.ht/~pierre-manchon/spp
Project-URL: repository, https://git.sr.ht/~pierre-manchon/spmp/
Project-URL: download, https://pypi.org/project/spmp/#files
Keywords: gis,gis-utils,tools
Classifier: Development Status :: 4 - Beta
Classifier: Intended Audience :: Developers
Classifier: Natural Language :: English
Classifier: Environment :: Console
Classifier: Operating System :: OS Independent
Classifier: License :: OSI Approved :: GNU General Public License v3 (GPLv3)
Classifier: Programming Language :: Python
Classifier: Programming Language :: Python :: 3
Classifier: Programming Language :: Python :: 3.8
Classifier: Programming Language :: Python :: 3.9
Classifier: Programming Language :: Python :: 3.10
Classifier: Programming Language :: Python :: 3.11
Classifier: Programming Language :: Python :: 3.12
Classifier: Programming Language :: Python :: 3 :: Only
Requires-Python: >=3.8
License-File: LICENSE
Provides-Extra: dev
Requires-Dist: pre-commit ; extra == 'dev'
Requires-Dist: pytest ; extra == 'dev'
Requires-Dist: tox ; extra == 'dev'
